libfrankapy/__init__.py
libfrankapy/_libfrankapy_core.cpython-311-x86_64-linux-gnu.so
libfrankapy/control.py
libfrankapy/exceptions.py
libfrankapy/robot.py
libfrankapy/state.py
libfrankapy/utils.py
libfrankapy-0.1.1.dist-info/LICENSE
libfrankapy-0.1.1.dist-info/METADATA
libfrankapy-0.1.1.dist-info/WHEEL
libfrankapy-0.1.1.dist-info/entry_points.txt
libfrankapy-0.1.1.dist-info/top_level.txt
libfrankapy-0.1.1.dist-info/RECORD
