Metadata-Version: 2.1
Name: libfrankapy
Version: 0.1.1
Summary: Python bindings for libfranka with real-time control
Home-page: https://github.com/libfrankapy/libfrankapy
Author: libfrankapy Team
Author-email: libfrankapy Team <support@libfrankapy.org>
Maintainer-email: libfrankapy Team <support@libfrankapy.org>
License: Apache-2.0
Project-URL: Homepage, https://github.com/libfrankapy/libfrankapy
Project-URL: Documentation, https://libfrankapy.readthedocs.io
Project-URL: Repository, https://github.com/libfrankapy/libfrankapy
Project-URL: Bug Tracker, https://github.com/libfrankapy/libfrankapy/issues
Project-URL: Changelog, https://github.com/libfrankapy/libfrankapy/blob/main/CHANGELOG.md
Keywords: robotics,franka,robot-control,real-time,panda
Classifier: Development Status :: 3 - Alpha
Classifier: Intended Audience :: Science/Research
Classifier: Intended Audience :: Developers
Classifier: Operating System :: POSIX :: Linux
Classifier: Programming Language :: Python :: 3
Classifier: Programming Language :: Python :: 3.9
Classifier: Programming Language :: Python :: 3.10
Classifier: Programming Language :: Python :: 3.11
Classifier: Programming Language :: C++
Classifier: Topic :: Scientific/Engineering :: Artificial Intelligence
Classifier: Topic :: Scientific/Engineering :: Physics
Classifier: Topic :: Software Development :: Libraries :: Python Modules
Requires-Python: >=3.9
License-File: LICENSE
Requires-Dist: numpy>=1.19.0
Requires-Dist: pybind11>=2.10.0
Provides-Extra: dev
Requires-Dist: pytest>=6.0; extra == "dev"
Requires-Dist: pytest-cov; extra == "dev"
Requires-Dist: black; extra == "dev"
Requires-Dist: isort; extra == "dev"
Requires-Dist: mypy; extra == "dev"
Requires-Dist: sphinx; extra == "dev"
Requires-Dist: sphinx-rtd-theme; extra == "dev"
Requires-Dist: pre-commit; extra == "dev"
Provides-Extra: docs
Requires-Dist: sphinx; extra == "docs"
Requires-Dist: sphinx-rtd-theme; extra == "docs"
Requires-Dist: myst-parser; extra == "docs"
Requires-Dist: sphinx-autodoc-typehints; extra == "docs"
Provides-Extra: examples
Requires-Dist: matplotlib; extra == "examples"
Requires-Dist: scipy; extra == "examples"
Requires-Dist: jupyter; extra == "examples"
Provides-Extra: test
Requires-Dist: pytest>=6.0; extra == "test"
Requires-Dist: pytest-cov>=2.10; extra == "test"
Requires-Dist: pytest-mock>=3.0; extra == "test"
Requires-Dist: coverage[toml]>=6.0; extra == "test"
Provides-Extra: testing
Requires-Dist: pytest>=6.0; extra == "testing"
Requires-Dist: pytest-cov; extra == "testing"
Requires-Dist: pytest-mock; extra == "testing"
